Cli/__init__.py
Cli/cli.py
localLlama/__init__.py
localLlama/server.py
local_llama-1.0.3.dist-info/METADATA
local_llama-1.0.3.dist-info/WHEEL
local_llama-1.0.3.dist-info/entry_points.txt
local_llama-1.0.3.dist-info/top_level.txt
local_llama-1.0.3.dist-info/RECORD
